fastt/__init__.py
fastt/cli.py
fastt/simple_logger.py
fastt-0.0.1.dist-info/entry_points.txt
fastt-0.0.1.dist-info/LICENSE
fastt-0.0.1.dist-info/WHEEL
fastt-0.0.1.dist-info/METADATA
fastt-0.0.1.dist-info/RECORD
