Metadata-Version: 2.1
Name: fastt
Version: 0.0.1
Summary: Fast and Simple Translation Tool
License: GPL-3.0
Author: Leandro E. Colombo Viña
Author-email: lecovi@ac.python.org.ar
Requires-Python: >=3.7,<4.0
Classifier: License :: OSI Approved :: GNU General Public License v3 (GPLv3)
Classifier: Programming Language :: Python :: 3
Classifier: Programming Language :: Python :: 3.7
Classifier: Programming Language :: Python :: 3.8
Requires-Dist: click (>=7.1.2,<8.0.0)
Requires-Dist: google-cloud-translate (==2.0.1)
Requires-Dist: polib (>=1.1.0,<2.0.0)
Requires-Dist: python-dotenv (>=0.13.0,<0.14.0)
